<?xml version="1.0" encoding="UTF-8" standalone="yes"?>
<workUser>
    <arrUsers>
        <address>
            <city>12.12.2012</city>
            <country>Usa</country>
        </address>
        <privateInformation>
            <name>bob4</name>
            <surname>Clark</surname>
            <bDay>2012-12-12</bDay>
        </privateInformation>
        <serviceInfo>
            <email>email@gmail.com</email>
            <login>sfsdf</login>
            <password>1234</password>
        </serviceInfo>
    </arrUsers>
</workUser>
